kismet/__init__.py
kismet/__main__.py
kismet/core.py
kismet/kismet.lark
kismet/parser.py
kismet/types.py
kismet/chatbot/discord.py
kismet/chatbot/slack.py
kismet/kernel/__main__.py
kismet/kernel/install.py
kismet/kernel/kernel.py
kismet/personality/core.py
kismet/personality/responses.py
kismet-0.9.0.dist-info/LICENSE
kismet-0.9.0.dist-info/WHEEL
kismet-0.9.0.dist-info/METADATA
kismet-0.9.0.dist-info/RECORD
